odoo/addons/eater/README.rst
odoo/addons/eater/__init__.py
odoo/addons/eater/__manifest__.py
odoo/addons/eater/demo/eaters.xml
odoo/addons/eater/i18n/eater.pot
odoo/addons/eater/i18n/fr.po
odoo/addons/eater/migrations/12.0.2.0.0/pre-migration.py
odoo/addons/eater/models/__init__.py
odoo/addons/eater/models/partner.py
odoo/addons/eater/readme/CONTRIBUTORS.rst
odoo/addons/eater/readme/DESCRIPTION.rst
odoo/addons/eater/security/ir.model.access.csv
odoo/addons/eater/static/description/index.html
odoo/addons/eater/tests/__init__.py
odoo/addons/eater/tests/test_partner.py
odoo/addons/eater/views/partner.xml
odoo/addons/eater/wizard/__init__.py
odoo/addons/eater/wizard/new_eater_wizard.py
odoo/addons/eater/wizard/new_eater_wizard_views.xml
odoo_addon_eater-16.0.1.0.0.14.dist-info/METADATA
odoo_addon_eater-16.0.1.0.0.14.dist-info/WHEEL
odoo_addon_eater-16.0.1.0.0.14.dist-info/top_level.txt
odoo_addon_eater-16.0.1.0.0.14.dist-info/RECORD
