Metadata-Version: 2.1
Name: odoo-addon-eater
Version: 16.0.1.0.0.14
Requires-Python: >=3.10
Requires-Dist: odoo-addon-partner_firstname>=16.0dev,<16.1dev
Requires-Dist: odoo>=16.0a,<16.1dev
Summary: Add eaters to the workers of your structure.
Home-page: https://github.com/beescoop/Obeesdoo
License: AGPL-3
Author: BEES coop - Cellule IT, Coop IT Easy SC
Classifier: Programming Language :: Python
Classifier: Framework :: Odoo
Classifier: Framework :: Odoo :: 16.0
Classifier: License :: OSI Approved :: GNU Affero General Public License v3
